EQL.py
Easy_QLearning-1.1.0.dist-info/METADATA
Easy_QLearning-1.1.0.dist-info/WHEEL
Easy_QLearning-1.1.0.dist-info/top_level.txt
Easy_QLearning-1.1.0.dist-info/RECORD
