Metadata-Version: 2.1
Name: Easy-QLearning
Version: 1.1.0
Summary: Simplify the creation of QLearning
Home-page: https://github.com/ProfesseurIssou/Easy-QLearning
Author: Hamidou Alix
Author-email: alix.hamidou@gmail.com
License: UNKNOWN
Platform: UNKNOWN
Classifier: Programming Language :: Python :: 3
Classifier: Programming Language :: Python :: 3.8
Classifier: Intended Audience :: Developers
Classifier: Intended Audience :: Science/Research
Classifier: License :: OSI Approved :: MIT License
Classifier: Operating System :: Microsoft :: Windows
Classifier: Operating System :: Unix
Requires-Dist: numpy (~=1.19)
Provides-Extra: dev
Requires-Dist: pytest (>=3.7) ; extra == 'dev'
